{"lieu":{"internal_id":"doctolib272247pid186998","departement":"91","location":{"longitude":2.4912535,"latitude":48.6215809,"city":"Saint-Germain-lès-Corbeil","cp":"91250"},"nom":"Centre de vaccination Covid-19 - Saint-Germain-lès-Corbeil","url":"https://www.doctolib.fr/centre-de-vaccinations-internationales/saint-germain-les-corbeil/centre-de-vaccination-covid-19-saint-germain-les-corbeil?pid=practice-186998","appointment_by_phone_only":false,"plateforme":"Doctolib","metadata":{"address":"Place Victor Hugo, 91250 Saint-Germain-lès-Corbeil","business_hours":{"lundi":null,"mardi":null,"mercredi":null,"jeudi":null,"vendredi":null,"samedi":null,"dimanche":null}},"type":"vaccination-center","vaccine_type":null},"stats":[{"date":"2021-05-19T18:24:18.432984+02:00","prochain_rdv":"2021-05-26T10:10:00.000+02:00","appointment_count":664,"chronodose_appointment_count":0},{"date":"2021-05-19T18:39:19.386112+02:00","prochain_rdv":"2021-05-27T10:30:00.000+02:00","appointment_count":655,"chronodose_appointment_count":0},{"date":"2021-05-19T18:59:38.922391+02:00","prochain_rdv":"2021-05-28T11:20:00.000+02:00","appointment_count":640,"chronodose_appointment_count":0},{"date":"2021-05-19T19:19:30.316393+02:00","prochain_rdv":"2021-05-31T09:40:00.000+02:00","appointment_count":689,"chronodose_appointment_count":0},{"date":"2021-05-19T19:39:08.359669+02:00","prochain_rdv":"2021-06-01T09:40:00.000+02:00","appointment_count":680,"chronodose_appointment_count":0},{"date":"2021-05-19T19:59:11.763089+02:00","prochain_rdv":"2021-06-01T11:00:00.000+02:00","appointment_count":636,"chronodose_appointment_count":0},{"date":"2021-05-19T20:18:55.994987+02:00","prochain_rdv":"2021-06-01T10:40:00.000+02:00","appointment_count":599,"chronodose_appointment_count":0},{"date":"2021-05-19T20:34:15.893440+02:00","prochain_rdv":"2021-06-02T11:30:00.000+02:00","appointment_count":605,"chronodose_appointment_count":0},{"date":"2021-05-19T20:53:06.266951+02:00","prochain_rdv":"2021-06-03T13:40:00.000+02:00","appointment_count":353,"chronodose_appointment_count":0},{"date":"2021-05-19T21:09:33.006450+02:00","prochain_rdv":"2021-06-03T09:50:00.000+02:00","appointment_count":340,"chronodose_appointment_count":0},{"date":"2021-05-19T21:28:16.365098+02:00","prochain_rdv":"2021-06-07T09:40:00.000+02:00","appointment_count":409,"chronodose_appointment_count":0},{"date":"2021-05-19T21:44:18.347967+02:00","prochain_rdv":"2021-06-07T12:10:00.000+02:00","appointment_count":378,"chronodose_appointment_count":0},{"date":"2021-05-19T21:59:53.349035+02:00","prochain_rdv":"2021-06-10T09:30:00.000+02:00","appointment_count":174,"chronodose_appointment_count":0},{"date":"2021-05-19T22:18:18.098873+02:00","prochain_rdv":"2021-06-10T11:00:00.000+02:00","appointment_count":140,"chronodose_appointment_count":0},{"date":"2021-05-19T22:34:39.152784+02:00","prochain_rdv":"2021-06-11T10:20:00.000+02:00","appointment_count":143,"chronodose_appointment_count":0},{"date":"2021-05-19T22:53:53.962312+02:00","prochain_rdv":"2021-06-11T10:40:00.000+02:00","appointment_count":138,"chronodose_appointment_count":0},{"date":"2021-05-19T23:06:36.424929+02:00","prochain_rdv":"2021-06-11T10:50:00.000+02:00","appointment_count":129,"chronodose_appointment_count":0},{"date":"2021-05-19T23:09:04.491790+02:00","prochain_rdv":"2021-06-14T10:20:00.000+02:00","appointment_count":171,"chronodose_appointment_count":0},{"date":"2021-05-19T23:14:46.978708+02:00","prochain_rdv":"2021-06-11T10:50:00.000+02:00","appointment_count":129,"chronodose_appointment_count":0},{"date":"2021-05-19T23:20:28.245961+02:00","prochain_rdv":"2021-06-11T09:50:00.000+02:00","appointment_count":117,"chronodose_appointment_count":0},{"date":"2021-05-19T23:39:23.296046+02:00","prochain_rdv":"2021-06-11T11:50:00.000+02:00","appointment_count":109,"chronodose_appointment_count":0},{"date":"2021-05-20T00:13:34.403933+02:00","prochain_rdv":"2021-06-14T09:00:00.000+02:00","appointment_count":154,"chronodose_appointment_count":0},{"date":"2021-05-20T00:19:03.940891+02:00","prochain_rdv":"2021-06-11T09:50:00.000+02:00","appointment_count":107,"chronodose_appointment_count":0},{"date":"2021-05-20T00:24:40.992900+02:00","prochain_rdv":"2021-06-14T09:00:00.000+02:00","appointment_count":154,"chronodose_appointment_count":0},{"date":"2021-05-20T00:49:07.031746+02:00","prochain_rdv":"2021-06-11T15:10:00.000+02:00","appointment_count":104,"chronodose_appointment_count":0},{"date":"2021-05-20T01:10:20.439284+02:00","prochain_rdv":"2021-06-14T10:00:00.000+02:00","appointment_count":149,"chronodose_appointment_count":0},{"date":"2021-05-20T01:28:53.688361+02:00","prochain_rdv":"2021-06-14T10:00:00.000+02:00","appointment_count":148,"chronodose_appointment_count":0},{"date":"2021-05-20T01:44:30.037081+02:00","prochain_rdv":"2021-06-14T10:00:00.000+02:00","appointment_count":146,"chronodose_appointment_count":0},{"date":"2021-05-20T02:19:20.917676+02:00","prochain_rdv":"2021-06-14T10:30:00.000+02:00","appointment_count":144,"chronodose_appointment_count":0},{"date":"2021-05-20T04:09:54.149605+02:00","prochain_rdv":"2021-06-14T10:30:00.000+02:00","appointment_count":142,"chronodose_appointment_count":0},{"date":"2021-05-20T04:34:43.798539+02:00","prochain_rdv":"2021-06-14T10:40:00.000+02:00","appointment_count":141,"chronodose_appointment_count":0},{"date":"2021-05-20T05:28:29.355272+02:00","prochain_rdv":"2021-06-14T11:30:00.000+02:00","appointment_count":138,"chronodose_appointment_count":0},{"date":"2021-05-20T06:28:42.913981+02:00","prochain_rdv":"2021-06-14T14:40:00.000+02:00","appointment_count":136,"chronodose_appointment_count":0},{"date":"2021-05-20T06:44:33.043280+02:00","prochain_rdv":"2021-06-14T11:30:00.000+02:00","appointment_count":130,"chronodose_appointment_count":0},{"date":"2021-05-20T06:48:36.788765+02:00","prochain_rdv":"2021-06-14T11:30:00.000+02:00","appointment_count":129,"chronodose_appointment_count":0},{"date":"2021-05-20T07:05:30.004980+02:00","prochain_rdv":"2021-06-14T11:30:00.000+02:00","appointment_count":125,"chronodose_appointment_count":0},{"date":"2021-05-20T07:09:47.223136+02:00","prochain_rdv":"2021-06-14T11:30:00.000+02:00","appointment_count":124,"chronodose_appointment_count":0},{"date":"2021-05-20T07:13:37.682974+02:00","prochain_rdv":"2021-06-14T11:30:00.000+02:00","appointment_count":125,"chronodose_appointment_count":0},{"date":"2021-05-20T07:24:24.016690+02:00","prochain_rdv":"2021-06-14T11:30:00.000+02:00","appointment_count":124,"chronodose_appointment_count":0},{"date":"2021-05-20T07:28:52.942204+02:00","prochain_rdv":"2021-06-15T10:40:00.000+02:00","appointment_count":148,"chronodose_appointment_count":0},{"date":"2021-05-20T07:34:02.819620+02:00","prochain_rdv":"2021-06-15T10:40:00.000+02:00","appointment_count":146,"chronodose_appointment_count":0},{"date":"2021-05-20T07:54:11.712304+02:00","prochain_rdv":"2021-06-15T13:30:00.000+02:00","appointment_count":135,"chronodose_appointment_count":0},{"date":"2021-05-20T08:10:12.473782+02:00","prochain_rdv":"2021-06-15T15:20:00.000+02:00","appointment_count":127,"chronodose_appointment_count":0},{"date":"2021-05-20T08:14:10.049640+02:00","prochain_rdv":"2021-06-15T14:50:00.000+02:00","appointment_count":128,"chronodose_appointment_count":0},{"date":"2021-05-20T08:18:55.411770+02:00","prochain_rdv":"2021-06-15T15:20:00.000+02:00","appointment_count":127,"chronodose_appointment_count":0},{"date":"2021-05-20T08:25:37.102536+02:00","prochain_rdv":"2021-06-15T14:20:00.000+02:00","appointment_count":124,"chronodose_appointment_count":0},{"date":"2021-05-20T08:28:09.026771+02:00","prochain_rdv":"2021-06-15T14:50:00.000+02:00","appointment_count":128,"chronodose_appointment_count":0},{"date":"2021-05-20T08:33:51.374330+02:00","prochain_rdv":"2021-06-15T14:20:00.000+02:00","appointment_count":124,"chronodose_appointment_count":0},{"date":"2021-05-20T08:44:28.100572+02:00","prochain_rdv":"2021-06-16T10:10:00.000+02:00","appointment_count":147,"chronodose_appointment_count":0},{"date":"2021-05-20T08:59:59.123716+02:00","prochain_rdv":"2021-06-09T09:50:00.000+02:00","appointment_count":177,"chronodose_appointment_count":0},{"date":"2021-05-20T09:14:41.222483+02:00","prochain_rdv":"2021-05-27T14:10:00.000+02:00","appointment_count":39,"chronodose_appointment_count":0},{"date":"2021-05-20T09:21:09.297587+02:00","prochain_rdv":"2021-06-09T09:50:00.000+02:00","appointment_count":163,"chronodose_appointment_count":0},{"date":"2021-05-20T09:25:33.867419+02:00","prochain_rdv":"2021-05-27T14:10:00.000+02:00","appointment_count":39,"chronodose_appointment_count":0},{"date":"2021-05-20T09:29:24.103108+02:00","prochain_rdv":"2021-06-09T09:50:00.000+02:00","appointment_count":163,"chronodose_appointment_count":0},{"date":"2021-05-20T09:39:48.892456+02:00","prochain_rdv":"2021-05-27T14:10:00.000+02:00","appointment_count":14,"chronodose_appointment_count":0},{"date":"2021-05-20T10:45:24.627742+02:00","prochain_rdv":"2021-06-14T11:00:00.000+02:00","appointment_count":57,"chronodose_appointment_count":0},{"date":"2021-05-20T10:59:28.315527+02:00","prochain_rdv":"2021-06-16T11:00:00.000+02:00","appointment_count":112,"chronodose_appointment_count":0},{"date":"2021-05-20T11:14:45.138544+02:00","prochain_rdv":"2021-06-17T10:50:00.000+02:00","appointment_count":144,"chronodose_appointment_count":0},{"date":"2021-05-20T11:34:45.426747+02:00","prochain_rdv":"2021-06-03T11:50:00.000+02:00","appointment_count":145,"chronodose_appointment_count":0},{"date":"2021-05-20T11:40:10.500103+02:00","prochain_rdv":"2021-06-17T10:50:00.000+02:00","appointment_count":139,"chronodose_appointment_count":0},{"date":"2021-05-20T11:59:40.588536+02:00","prochain_rdv":"2021-06-08T09:10:00.000+02:00","appointment_count":107,"chronodose_appointment_count":0},{"date":"2021-05-20T12:03:56.597060+02:00","prochain_rdv":"2021-06-17T11:10:00.000+02:00","appointment_count":138,"chronodose_appointment_count":0},{"date":"2021-05-20T12:10:40.143893+02:00","prochain_rdv":"2021-06-08T09:10:00.000+02:00","appointment_count":107,"chronodose_appointment_count":0},{"date":"2021-05-20T12:18:33.721252+02:00","prochain_rdv":"2021-06-17T10:50:00.000+02:00","appointment_count":135,"chronodose_appointment_count":0},{"date":"2021-05-20T12:33:52.261522+02:00","prochain_rdv":"2021-06-17T11:50:00.000+02:00","appointment_count":131,"chronodose_appointment_count":0},{"date":"2021-05-20T12:53:54.187654+02:00","prochain_rdv":"2021-06-17T10:50:00.000+02:00","appointment_count":123,"chronodose_appointment_count":0},{"date":"2021-05-20T13:10:06.582744+02:00","prochain_rdv":"2021-06-17T10:50:00.000+02:00","appointment_count":112,"chronodose_appointment_count":0},{"date":"2021-05-20T13:30:06.785847+02:00","prochain_rdv":null,"appointment_count":0,"chronodose_appointment_count":0},{"date":"2021-05-20T15:05:08.942825+02:00","prochain_rdv":"2021-06-03T09:00:00.000+02:00","appointment_count":164,"chronodose_appointment_count":0},{"date":"2021-05-20T15:14:20.002486+02:00","prochain_rdv":null,"appointment_count":0,"chronodose_appointment_count":0},{"date":"2021-05-20T15:51:56.801710+02:00","prochain_rdv":"2021-06-21T15:40:00.000+02:00","appointment_count":118,"chronodose_appointment_count":0},{"date":"2021-05-20T15:53:46.580449+02:00","prochain_rdv":"2021-06-21T15:40:00.000+02:00","appointment_count":1,"chronodose_appointment_count":0},{"date":"2021-05-20T16:04:33.209658+02:00","prochain_rdv":"2021-06-21T15:40:00.000+02:00","appointment_count":118,"chronodose_appointment_count":0},{"date":"2021-05-20T16:11:10.035077+02:00","prochain_rdv":"2021-06-03T09:00:00.000+02:00","appointment_count":158,"chronodose_appointment_count":0},{"date":"2021-05-20T16:33:26.305150+02:00","prochain_rdv":null,"appointment_count":0,"chronodose_appointment_count":0}]}