{"lieu":{"internal_id":"doctolib244790pid166399","departement":"94","location":{"longitude":2.437625,"latitude":48.816287,"city":"Maisons-Alfort","cp":"94700"},"nom":"Centre de Vaccination COVID - [Maisons-Alfort]","url":"https://www.doctolib.fr/vaccination-covid-19/maisons-alfort/centre-de-vaccination-covid-maisons-alfort?pid=practice-166399","appointment_by_phone_only":false,"plateforme":"Doctolib","metadata":{"address":"47 Avenue Foch, 94700 Maisons-Alfort","business_hours":{"lundi":"09:00-12:00, 14:00-18:00","mardi":"09:00-12:00, 14:00-18:00","mercredi":"09:00-12:00, 14:00-18:00","jeudi":"09:00-12:00, 14:00-18:00","vendredi":"09:00-12:00, 14:00-18:00","samedi":null,"dimanche":null},"phone_number":"+33805040994"},"type":"vaccination-center","vaccine_type":null},"stats":[{"date":"2021-05-17T00:14:28.377693+02:00","prochain_rdv":null,"appointment_count":0,"chronodose_appointment_count":0},{"date":"2021-05-22T10:18:51.785107+02:00","prochain_rdv":"2021-05-24T09:00:00.000+02:00","appointment_count":112,"chronodose_appointment_count":0},{"date":"2021-05-22T10:34:20.949143+02:00","prochain_rdv":"2021-05-24T09:40:00.000+02:00","appointment_count":108,"chronodose_appointment_count":0},{"date":"2021-05-22T10:44:57.924382+02:00","prochain_rdv":"2021-05-24T09:10:00.000+02:00","appointment_count":107,"chronodose_appointment_count":0},{"date":"2021-05-22T10:48:41.340711+02:00","prochain_rdv":"2021-05-24T09:40:00.000+02:00","appointment_count":108,"chronodose_appointment_count":0},{"date":"2021-05-22T10:54:04.283419+02:00","prochain_rdv":"2021-05-24T09:20:00.000+02:00","appointment_count":103,"chronodose_appointment_count":0},{"date":"2021-05-22T11:10:37.531426+02:00","prochain_rdv":"2021-05-24T12:00:00.000+02:00","appointment_count":93,"chronodose_appointment_count":0},{"date":"2021-05-22T11:29:19.271465+02:00","prochain_rdv":"2021-05-24T12:30:00.000+02:00","appointment_count":82,"chronodose_appointment_count":0},{"date":"2021-05-22T11:33:56.993441+02:00","prochain_rdv":"2021-05-24T13:10:00.000+02:00","appointment_count":83,"chronodose_appointment_count":0},{"date":"2021-05-22T11:40:04.917008+02:00","prochain_rdv":"2021-05-24T12:30:00.000+02:00","appointment_count":82,"chronodose_appointment_count":0},{"date":"2021-05-22T11:43:36.315459+02:00","prochain_rdv":"2021-05-24T13:10:00.000+02:00","appointment_count":83,"chronodose_appointment_count":0},{"date":"2021-05-22T11:54:17.574175+02:00","prochain_rdv":"2021-05-24T14:20:00.000+02:00","appointment_count":74,"chronodose_appointment_count":0},{"date":"2021-05-22T12:09:47.314165+02:00","prochain_rdv":"2021-05-24T15:10:00.000+02:00","appointment_count":68,"chronodose_appointment_count":0},{"date":"2021-05-22T12:28:53.480908+02:00","prochain_rdv":"2021-05-24T11:20:00.000+02:00","appointment_count":77,"chronodose_appointment_count":0},{"date":"2021-05-22T12:44:22.934338+02:00","prochain_rdv":"2021-05-24T16:50:00.000+02:00","appointment_count":58,"chronodose_appointment_count":0},{"date":"2021-05-22T13:03:43.438307+02:00","prochain_rdv":"2021-05-25T09:20:00.000+02:00","appointment_count":50,"chronodose_appointment_count":0},{"date":"2021-05-22T13:10:38.986933+02:00","prochain_rdv":"2021-05-25T09:20:00.000+02:00","appointment_count":47,"chronodose_appointment_count":0},{"date":"2021-05-22T13:14:15.101107+02:00","prochain_rdv":"2021-05-25T09:20:00.000+02:00","appointment_count":50,"chronodose_appointment_count":0},{"date":"2021-05-22T13:19:04.650011+02:00","prochain_rdv":"2021-05-25T09:40:00.000+02:00","appointment_count":45,"chronodose_appointment_count":0},{"date":"2021-05-22T13:39:40.912158+02:00","prochain_rdv":"2021-05-25T09:50:00.000+02:00","appointment_count":43,"chronodose_appointment_count":0},{"date":"2021-05-22T13:44:44.384592+02:00","prochain_rdv":"2021-05-25T10:10:00.000+02:00","appointment_count":42,"chronodose_appointment_count":0},{"date":"2021-05-22T13:49:09.416416+02:00","prochain_rdv":"2021-05-25T09:50:00.000+02:00","appointment_count":43,"chronodose_appointment_count":0},{"date":"2021-05-22T13:59:30.565516+02:00","prochain_rdv":"2021-05-25T09:50:00.000+02:00","appointment_count":41,"chronodose_appointment_count":0},{"date":"2021-05-22T14:14:27.713665+02:00","prochain_rdv":"2021-05-25T10:50:00.000+02:00","appointment_count":36,"chronodose_appointment_count":0},{"date":"2021-05-22T14:34:46.964820+02:00","prochain_rdv":"2021-05-25T11:40:00.000+02:00","appointment_count":26,"chronodose_appointment_count":0},{"date":"2021-05-22T14:49:02.361465+02:00","prochain_rdv":"2021-05-25T10:40:00.000+02:00","appointment_count":22,"chronodose_appointment_count":0},{"date":"2021-05-22T14:54:30.098882+02:00","prochain_rdv":"2021-05-25T13:20:00.000+02:00","appointment_count":17,"chronodose_appointment_count":0},{"date":"2021-05-22T15:04:20.874504+02:00","prochain_rdv":"2021-05-25T13:40:00.000+02:00","appointment_count":15,"chronodose_appointment_count":0},{"date":"2021-05-22T15:09:25.921874+02:00","prochain_rdv":"2021-05-25T13:20:00.000+02:00","appointment_count":17,"chronodose_appointment_count":0},{"date":"2021-05-22T15:14:17.166094+02:00","prochain_rdv":"2021-05-25T14:20:00.000+02:00","appointment_count":8,"chronodose_appointment_count":0},{"date":"2021-05-22T15:28:53.862889+02:00","prochain_rdv":"2021-05-25T13:50:00.000+02:00","appointment_count":5,"chronodose_appointment_count":0},{"date":"2021-05-22T15:39:31.145674+02:00","prochain_rdv":"2021-05-25T15:20:00.000+02:00","appointment_count":2,"chronodose_appointment_count":0},{"date":"2021-05-22T15:58:30.153601+02:00","prochain_rdv":"2021-05-24T10:40:00.000+02:00","appointment_count":3,"chronodose_appointment_count":0},{"date":"2021-05-22T16:14:26.999702+02:00","prochain_rdv":null,"appointment_count":0,"chronodose_appointment_count":0},{"date":"2021-05-22T16:19:40.891391+02:00","prochain_rdv":"2021-05-25T15:50:00.000+02:00","appointment_count":1,"chronodose_appointment_count":0},{"date":"2021-05-22T16:39:46.003776+02:00","prochain_rdv":null,"appointment_count":0,"chronodose_appointment_count":0},{"date":"2021-05-22T16:48:57.745378+02:00","prochain_rdv":"2021-05-25T16:20:00.000+02:00","appointment_count":1,"chronodose_appointment_count":0},{"date":"2021-05-22T17:03:51.364632+02:00","prochain_rdv":"2021-05-25T12:50:00.000+02:00","appointment_count":2,"chronodose_appointment_count":0},{"date":"2021-05-22T17:09:04.874428+02:00","prochain_rdv":"2021-05-25T14:10:00.000+02:00","appointment_count":5,"chronodose_appointment_count":0},{"date":"2021-05-22T17:18:31.640546+02:00","prochain_rdv":"2021-05-25T12:50:00.000+02:00","appointment_count":2,"chronodose_appointment_count":0},{"date":"2021-05-22T17:24:03.070420+02:00","prochain_rdv":"2021-05-25T14:10:00.000+02:00","appointment_count":5,"chronodose_appointment_count":0},{"date":"2021-05-22T17:28:41.425049+02:00","prochain_rdv":"2021-05-25T16:20:00.000+02:00","appointment_count":3,"chronodose_appointment_count":0},{"date":"2021-05-22T17:43:25.225130+02:00","prochain_rdv":"2021-05-25T16:40:00.000+02:00","appointment_count":2,"chronodose_appointment_count":0},{"date":"2021-05-22T17:49:29.631941+02:00","prochain_rdv":null,"appointment_count":0,"chronodose_appointment_count":0},{"date":"2021-05-22T18:04:47.464480+02:00","prochain_rdv":"2021-05-25T16:20:00.000+02:00","appointment_count":1,"chronodose_appointment_count":0},{"date":"2021-05-23T01:44:41.304940+02:00","prochain_rdv":null,"appointment_count":0,"chronodose_appointment_count":0},{"date":"2021-05-23T02:04:40.722076+02:00","prochain_rdv":"2021-05-24T09:40:00.000+02:00","appointment_count":1,"chronodose_appointment_count":1},{"date":"2021-05-23T02:24:27.480720+02:00","prochain_rdv":null,"appointment_count":0,"chronodose_appointment_count":0},{"date":"2021-05-23T09:10:09.189517+02:00","prochain_rdv":"2021-05-24T10:10:00.000+02:00","appointment_count":1,"chronodose_appointment_count":1},{"date":"2021-05-23T09:28:30.748202+02:00","prochain_rdv":null,"appointment_count":0,"chronodose_appointment_count":0},{"date":"2021-05-23T10:58:44.448931+02:00","prochain_rdv":"2021-05-25T11:30:00.000+02:00","appointment_count":1,"chronodose_appointment_count":0},{"date":"2021-05-23T11:14:51.944417+02:00","prochain_rdv":null,"appointment_count":0,"chronodose_appointment_count":0},{"date":"2021-05-23T13:09:19.152902+02:00","prochain_rdv":"2021-05-26T11:30:00.000+02:00","appointment_count":1,"chronodose_appointment_count":0},{"date":"2021-05-23T13:13:43.448928+02:00","prochain_rdv":null,"appointment_count":0,"chronodose_appointment_count":0}]}