{"lieu":{"internal_id":"doctolib242860pid164847","departement":"58","location":{"longitude":3.0206832,"latitude":47.1763568,"city":"La Charité-sur-Loire","cp":"58400"},"nom":"Centre de vaccination de La Charité-Sur-Loire","url":"https://www.doctolib.fr/vaccination-covid-19/la-charite-sur-loire/centre-de-vaccination-de-la-charite-sur-loire?pid=practice-164847","appointment_by_phone_only":false,"plateforme":"Doctolib","metadata":{"address":"40 Rue Sainte-Anne, 58400 La Charité-sur-Loire","business_hours":{"lundi":"09:00-12:00","mardi":"09:00-12:00","mercredi":"09:00-12:00","jeudi":"09:00-12:00","vendredi":"09:00-12:00","samedi":null,"dimanche":null},"phone_number":"+33345640210"},"type":"vaccination-center","vaccine_type":["Pfizer-BioNTech"]},"stats":[{"date":"2021-05-17T00:14:28.266669+02:00","prochain_rdv":null,"appointment_count":0,"chronodose_appointment_count":0},{"date":"2021-05-17T10:59:02.927393+02:00","prochain_rdv":"2021-05-17T14:30:00.000+02:00","appointment_count":1,"chronodose_appointment_count":1},{"date":"2021-05-17T11:09:58.971456+02:00","prochain_rdv":null,"appointment_count":0,"chronodose_appointment_count":0},{"date":"2021-05-17T11:19:33.580508+02:00","prochain_rdv":"2021-05-17T14:30:00.000+02:00","appointment_count":1,"chronodose_appointment_count":1},{"date":"2021-05-17T11:29:06.290229+02:00","prochain_rdv":null,"appointment_count":0,"chronodose_appointment_count":0},{"date":"2021-05-17T12:23:56.858681+02:00","prochain_rdv":"2021-05-18T10:30:00.000+02:00","appointment_count":1,"chronodose_appointment_count":1},{"date":"2021-05-17T12:56:17.462242+02:00","prochain_rdv":null,"appointment_count":0,"chronodose_appointment_count":0},{"date":"2021-05-17T17:21:16.682867+02:00","prochain_rdv":"2021-05-20T10:15:00.000+02:00","appointment_count":10,"chronodose_appointment_count":0},{"date":"2021-05-17T17:26:06.075820+02:00","prochain_rdv":null,"appointment_count":0,"chronodose_appointment_count":0},{"date":"2021-05-17T17:29:26.564256+02:00","prochain_rdv":"2021-05-20T10:15:00.000+02:00","appointment_count":10,"chronodose_appointment_count":0},{"date":"2021-05-17T17:55:12.355040+02:00","prochain_rdv":"2021-05-22T10:45:00.000+02:00","appointment_count":1,"chronodose_appointment_count":0},{"date":"2021-05-17T17:59:40.603188+02:00","prochain_rdv":null,"appointment_count":0,"chronodose_appointment_count":0},{"date":"2021-05-17T18:11:12.847783+02:00","prochain_rdv":"2021-05-22T10:45:00.000+02:00","appointment_count":2,"chronodose_appointment_count":0},{"date":"2021-05-17T18:14:09.711186+02:00","prochain_rdv":"2021-06-03T13:30:00.000+02:00","appointment_count":1,"chronodose_appointment_count":0},{"date":"2021-05-17T18:41:56.095887+02:00","prochain_rdv":null,"appointment_count":0,"chronodose_appointment_count":0},{"date":"2021-05-17T18:55:25.760878+02:00","prochain_rdv":"2021-06-03T14:00:00.000+02:00","appointment_count":1,"chronodose_appointment_count":0},{"date":"2021-05-17T19:25:51.943869+02:00","prochain_rdv":null,"appointment_count":0,"chronodose_appointment_count":0},{"date":"2021-05-17T22:25:09.030490+02:00","prochain_rdv":"2021-06-02T16:15:00.000+02:00","appointment_count":1,"chronodose_appointment_count":0},{"date":"2021-05-17T22:30:00.971655+02:00","prochain_rdv":null,"appointment_count":0,"chronodose_appointment_count":0},{"date":"2021-05-17T22:34:41.500124+02:00","prochain_rdv":"2021-06-02T16:15:00.000+02:00","appointment_count":1,"chronodose_appointment_count":0},{"date":"2021-05-17T22:49:38.092833+02:00","prochain_rdv":null,"appointment_count":0,"chronodose_appointment_count":0},{"date":"2021-05-18T11:32:09.134387+02:00","prochain_rdv":"2021-05-20T10:15:00.000+02:00","appointment_count":10,"chronodose_appointment_count":0},{"date":"2021-05-18T11:50:15.470676+02:00","prochain_rdv":null,"appointment_count":0,"chronodose_appointment_count":0},{"date":"2021-05-18T11:55:55.694671+02:00","prochain_rdv":"2021-05-20T10:15:00.000+02:00","appointment_count":8,"chronodose_appointment_count":0},{"date":"2021-05-18T12:17:01.720649+02:00","prochain_rdv":null,"appointment_count":0,"chronodose_appointment_count":0},{"date":"2021-05-18T13:02:26.235197+02:00","prochain_rdv":"2021-05-20T10:45:00.000+02:00","appointment_count":8,"chronodose_appointment_count":0},{"date":"2021-05-18T13:12:36.709673+02:00","prochain_rdv":null,"appointment_count":0,"chronodose_appointment_count":0},{"date":"2021-05-18T13:29:07.288162+02:00","prochain_rdv":"2021-05-20T11:00:00.000+02:00","appointment_count":7,"chronodose_appointment_count":0},{"date":"2021-05-18T13:45:05.398659+02:00","prochain_rdv":null,"appointment_count":0,"chronodose_appointment_count":0},{"date":"2021-05-18T17:30:16.440774+02:00","prochain_rdv":"2021-05-26T13:30:00.000+02:00","appointment_count":4,"chronodose_appointment_count":0},{"date":"2021-05-18T17:34:56.234301+02:00","prochain_rdv":null,"appointment_count":0,"chronodose_appointment_count":0},{"date":"2021-05-18T19:59:52.571991+02:00","prochain_rdv":"2021-05-26T15:30:00.000+02:00","appointment_count":4,"chronodose_appointment_count":0},{"date":"2021-05-18T20:14:25.256863+02:00","prochain_rdv":null,"appointment_count":0,"chronodose_appointment_count":0},{"date":"2021-05-18T21:49:14.017687+02:00","prochain_rdv":"2021-06-03T15:15:00.000+02:00","appointment_count":1,"chronodose_appointment_count":0},{"date":"2021-05-18T21:54:24.613810+02:00","prochain_rdv":"2021-06-03T15:15:00.000+02:00","appointment_count":2,"chronodose_appointment_count":0},{"date":"2021-05-18T22:04:21.008924+02:00","prochain_rdv":null,"appointment_count":0,"chronodose_appointment_count":0},{"date":"2021-05-19T06:49:42.642180+02:00","prochain_rdv":"2021-05-25T09:00:00.000+02:00","appointment_count":4,"chronodose_appointment_count":0},{"date":"2021-05-19T06:54:54.059654+02:00","prochain_rdv":null,"appointment_count":0,"chronodose_appointment_count":0},{"date":"2021-05-19T07:04:53.095848+02:00","prochain_rdv":"2021-05-25T09:00:00.000+02:00","appointment_count":4,"chronodose_appointment_count":0},{"date":"2021-05-19T07:24:28.420506+02:00","prochain_rdv":null,"appointment_count":0,"chronodose_appointment_count":0},{"date":"2021-05-19T11:40:15.995068+02:00","prochain_rdv":"2021-06-12T09:00:00.000+02:00","appointment_count":1,"chronodose_appointment_count":0},{"date":"2021-05-19T12:00:12.999384+02:00","prochain_rdv":null,"appointment_count":0,"chronodose_appointment_count":0},{"date":"2021-05-19T17:14:37.036911+02:00","prochain_rdv":"2021-06-04T08:15:00.000+02:00","appointment_count":28,"chronodose_appointment_count":0},{"date":"2021-05-19T17:24:48.533111+02:00","prochain_rdv":null,"appointment_count":0,"chronodose_appointment_count":0},{"date":"2021-05-20T10:59:28.197504+02:00","prochain_rdv":"2021-06-08T10:15:00.000+02:00","appointment_count":1,"chronodose_appointment_count":0},{"date":"2021-05-20T11:14:45.024967+02:00","prochain_rdv":null,"appointment_count":0,"chronodose_appointment_count":0},{"date":"2021-05-21T17:28:57.471277+02:00","prochain_rdv":"2021-06-11T15:30:00.000+02:00","appointment_count":1,"chronodose_appointment_count":0},{"date":"2021-05-21T17:48:58.104851+02:00","prochain_rdv":"2021-05-31T16:30:00.000+02:00","appointment_count":77,"chronodose_appointment_count":0},{"date":"2021-05-21T17:59:53.104963+02:00","prochain_rdv":"2021-06-02T13:30:00.000+02:00","appointment_count":72,"chronodose_appointment_count":0},{"date":"2021-05-21T18:20:42.286654+02:00","prochain_rdv":"2021-06-02T13:45:00.000+02:00","appointment_count":63,"chronodose_appointment_count":0},{"date":"2021-05-21T18:24:02.473434+02:00","prochain_rdv":"2021-06-02T13:45:00.000+02:00","appointment_count":79,"chronodose_appointment_count":0},{"date":"2021-05-21T18:28:28.238293+02:00","prochain_rdv":"2021-06-02T13:45:00.000+02:00","appointment_count":80,"chronodose_appointment_count":0},{"date":"2021-05-21T18:34:47.070975+02:00","prochain_rdv":"2021-06-02T13:45:00.000+02:00","appointment_count":79,"chronodose_appointment_count":0},{"date":"2021-05-21T18:39:32.510328+02:00","prochain_rdv":"2021-06-02T13:45:00.000+02:00","appointment_count":80,"chronodose_appointment_count":0},{"date":"2021-05-21T18:45:04.598239+02:00","prochain_rdv":"2021-06-02T13:45:00.000+02:00","appointment_count":79,"chronodose_appointment_count":0},{"date":"2021-05-21T19:00:00.041389+02:00","prochain_rdv":"2021-06-02T14:00:00.000+02:00","appointment_count":76,"chronodose_appointment_count":0},{"date":"2021-05-21T19:04:29.638762+02:00","prochain_rdv":"2021-06-02T14:00:00.000+02:00","appointment_count":75,"chronodose_appointment_count":0},{"date":"2021-05-21T19:09:43.260105+02:00","prochain_rdv":"2021-06-02T14:00:00.000+02:00","appointment_count":77,"chronodose_appointment_count":0},{"date":"2021-05-21T19:14:09.944243+02:00","prochain_rdv":"2021-06-02T14:00:00.000+02:00","appointment_count":76,"chronodose_appointment_count":0},{"date":"2021-05-21T19:24:37.375700+02:00","prochain_rdv":"2021-06-02T14:15:00.000+02:00","appointment_count":67,"chronodose_appointment_count":0},{"date":"2021-05-21T19:40:21.749241+02:00","prochain_rdv":"2021-06-02T14:45:00.000+02:00","appointment_count":61,"chronodose_appointment_count":0},{"date":"2021-05-21T19:49:11.917481+02:00","prochain_rdv":"2021-06-02T15:30:00.000+02:00","appointment_count":59,"chronodose_appointment_count":0},{"date":"2021-05-21T19:54:18.032980+02:00","prochain_rdv":"2021-06-02T14:45:00.000+02:00","appointment_count":63,"chronodose_appointment_count":0},{"date":"2021-05-21T19:58:59.542375+02:00","prochain_rdv":"2021-06-03T13:30:00.000+02:00","appointment_count":57,"chronodose_appointment_count":0},{"date":"2021-05-21T20:03:32.780539+02:00","prochain_rdv":"2021-06-02T15:30:00.000+02:00","appointment_count":59,"chronodose_appointment_count":0},{"date":"2021-05-21T20:10:34.423235+02:00","prochain_rdv":"2021-06-03T13:30:00.000+02:00","appointment_count":57,"chronodose_appointment_count":0},{"date":"2021-05-21T20:14:14.440344+02:00","prochain_rdv":"2021-06-02T15:30:00.000+02:00","appointment_count":47,"chronodose_appointment_count":0},{"date":"2021-05-21T20:34:15.933315+02:00","prochain_rdv":"2021-06-03T14:45:00.000+02:00","appointment_count":39,"chronodose_appointment_count":0},{"date":"2021-05-21T20:44:24.916280+02:00","prochain_rdv":"2021-06-03T14:30:00.000+02:00","appointment_count":35,"chronodose_appointment_count":0},{"date":"2021-05-21T20:48:36.794154+02:00","prochain_rdv":"2021-06-03T14:45:00.000+02:00","appointment_count":39,"chronodose_appointment_count":0},{"date":"2021-05-21T20:54:07.482817+02:00","prochain_rdv":"2021-06-03T14:30:00.000+02:00","appointment_count":35,"chronodose_appointment_count":0},{"date":"2021-05-21T20:59:18.828641+02:00","prochain_rdv":"2021-06-03T15:15:00.000+02:00","appointment_count":29,"chronodose_appointment_count":0},{"date":"2021-05-21T21:03:21.968506+02:00","prochain_rdv":"2021-06-03T15:15:00.000+02:00","appointment_count":28,"chronodose_appointment_count":0},{"date":"2021-05-21T21:10:51.120542+02:00","prochain_rdv":"2021-06-03T15:15:00.000+02:00","appointment_count":29,"chronodose_appointment_count":0},{"date":"2021-05-21T21:14:32.352566+02:00","prochain_rdv":"2021-06-03T15:15:00.000+02:00","appointment_count":28,"chronodose_appointment_count":0},{"date":"2021-05-21T21:18:37.575618+02:00","prochain_rdv":"2021-06-03T15:30:00.000+02:00","appointment_count":27,"chronodose_appointment_count":0},{"date":"2021-05-21T21:25:00.409338+02:00","prochain_rdv":"2021-06-03T16:15:00.000+02:00","appointment_count":25,"chronodose_appointment_count":0},{"date":"2021-05-21T21:29:03.903111+02:00","prochain_rdv":"2021-06-03T15:30:00.000+02:00","appointment_count":27,"chronodose_appointment_count":0},{"date":"2021-05-21T21:33:58.343319+02:00","prochain_rdv":"2021-06-03T16:15:00.000+02:00","appointment_count":25,"chronodose_appointment_count":0},{"date":"2021-05-21T21:39:12.971060+02:00","prochain_rdv":"2021-06-03T16:15:00.000+02:00","appointment_count":22,"chronodose_appointment_count":0},{"date":"2021-05-21T21:44:47.795227+02:00","prochain_rdv":"2021-06-03T16:15:00.000+02:00","appointment_count":23,"chronodose_appointment_count":0}]}