{"lieu":{"internal_id":"doctolib241961pid163935","departement":"91","location":{"longitude":2.075534,"latitude":48.64784,"city":"Limours","cp":"91470"},"nom":"Centre de vaccination Covid-19 de Limours","url":"https://www.doctolib.fr/vaccination-covid-19/briis-sous-forges/centre-de-vaccination-du-hurepoix?pid=practice-163935","appointment_by_phone_only":false,"plateforme":"Doctolib","metadata":{"address":"Rue de la Brelandière, 91470 Limours","business_hours":{"lundi":"09:00-12:30, 14:00-17:00","mardi":"09:00-12:30, 14:00-17:00","mercredi":"14:00-17:00","jeudi":"09:00-12:30, 14:00-17:00","vendredi":"14:00-17:00","samedi":null,"dimanche":null},"phone_number":"+33800009110"},"type":"vaccination-center","vaccine_type":["Pfizer-BioNTech"]},"statsLieuSurDernieresSecondes":[{"date":"2021-05-21T17:48:58.233338+02:00","prochain_rdv":null,"appointment_count":0,"chronodose_appointment_count":0},{"date":"2021-05-21T18:11:01.520622+02:00","prochain_rdv":"2021-05-25T09:15:00.000+02:00","appointment_count":27,"chronodose_appointment_count":0},{"date":"2021-05-21T18:13:37.675190+02:00","prochain_rdv":null,"appointment_count":0,"chronodose_appointment_count":0},{"date":"2021-05-21T18:20:42.406069+02:00","prochain_rdv":"2021-05-22T17:15:00.000+02:00","appointment_count":3,"chronodose_appointment_count":3},{"date":"2021-05-21T18:24:02.574662+02:00","prochain_rdv":"2021-05-25T09:15:00.000+02:00","appointment_count":27,"chronodose_appointment_count":0},{"date":"2021-05-21T18:28:28.361876+02:00","prochain_rdv":"2021-05-22T17:15:00.000+02:00","appointment_count":3,"chronodose_appointment_count":3}],"coefsDirecteur":[{"coefDirecteurStandard":0.00002040373705779623,"coefDirecteurChronodose":0,"duree":1323287},{"coefDirecteurStandard":0.0001729051263168006,"coefDirecteurChronodose":0,"duree":156155},{"coefDirecteurStandard":0.0000070632941791392666,"coefDirecteurChronodose":0.0000070632941791392666,"duree":424731},{"coefDirecteurStandard":0.00011989928460093521,"coefDirecteurChronodose":0.000014987410575116901,"duree":200168},{"coefDirecteurStandard":0.00009029787009898904,"coefDirecteurChronodose":0.00001128723376237363,"duree":265787}],"moyenneCoefsDirecteursStandardParMinute":2.6580842891185625,"moyenneCoefsDirecteursChronodoseParMinute":0.22783579621016248}