{"lieu":{"internal_id":"keldoc2085","departement":"974","location":{"longitude":55.4266,"latitude":-21.3182,"city":"Saint-Pierre","cp":"97410"},"nom":"Centre de vaccination Covid-19 aéroport de Pierrefonds","url":"https://vaccination-covid.keldoc.com/cabinet-medical/le-tampon-97418/centre-de-vaccination-covid-19-aeroport-de-pierrefonds","appointment_by_phone_only":false,"plateforme":"Keldoc","metadata":{"address":"34 Chemin de l’Aerodrome, 97410 Saint-Pierre","business_hours":{"lundi":"08:30-12:35/14:00-18:00","mardi":"08:30-12:35/14:00-18:00","mercredi":"08:30-12:35/14:00-18:00","jeudi":"08:30-12:35/14:00-18:00","vendredi":"08:30-12:35/14:00-18:00","samedi":"08:30-12:35/14:00-18:00","dimanche":"fermé"},"phone_number":"+33262720404"},"type":"vaccination-center","vaccine_type":["Pfizer-BioNTech"]},"statsLieuSurDernieresSecondes":[{"date":"2021-05-20T15:51:56.830574+02:00","prochain_rdv":"2021-05-21T11:35:00.000000+0200","appointment_count":1672,"chronodose_appointment_count":12},{"date":"2021-05-20T15:53:46.605135+02:00","prochain_rdv":"2021-05-21T11:05:00.000000+0200","appointment_count":1677,"chronodose_appointment_count":14},{"date":"2021-05-20T15:58:49.590288+02:00","prochain_rdv":"2021-05-21T11:05:00.000000+0200","appointment_count":1672,"chronodose_appointment_count":13},{"date":"2021-05-20T16:11:10.065627+02:00","prochain_rdv":"2021-05-21T11:35:00.000000+0200","appointment_count":1669,"chronodose_appointment_count":10},{"date":"2021-05-20T16:33:26.330743+02:00","prochain_rdv":"2021-05-21T11:04:00.000000+0200","appointment_count":1664,"chronodose_appointment_count":8},{"date":"2021-05-20T16:40:13.324460+02:00","prochain_rdv":"2021-05-21T11:04:00.000000+0200","appointment_count":1660,"chronodose_appointment_count":8}],"coefsDirecteur":[{"coefDirecteurStandard":0.000045547711227510815,"coefDirecteurChronodose":0.000018219084491004328,"duree":109775},{"coefDirecteurStandard":0.000016502467118834267,"coefDirecteurChronodose":0.000003300493423766853,"duree":302985},{"coefDirecteurStandard":0.000004051453458928391,"coefDirecteurChronodose":0.000004051453458928391,"duree":740475},{"coefDirecteurStandard":0.0000037417727771063375,"coefDirecteurChronodose":0.000001496709110842535,"duree":1336265},{"coefDirecteurStandard":0.00000982815471481152,"coefDirecteurChronodose":0,"duree":406994}],"moyenneCoefsDirecteursStandardParMinute":0.4557233676299692,"moyenneCoefsDirecteursChronodoseParMinute":0.1657175882290797}