{"lieu":{"internal_id":"keldoc2286","departement":"972","location":{"longitude":-60.9962,"latitude":14.6117,"city":"Le Lamentin","cp":"97232"},"nom":"Centre de vaccination du Hall des sports du Lamentin","url":"https://vaccination-covid.keldoc.com/cabinet-medical/fort-de-france-97200/centre-de-vaccination-du-lamentin","appointment_by_phone_only":false,"plateforme":"Keldoc","metadata":{"address":" Hall des sports - Place d'Armes, 97232 Le Lamentin","business_hours":{"lundi":"7H30 à 19H","mardi":"7H30 à 19H","mercredi":"7H30 à 19H","jeudi":"7H30 à 19H","vendredi":"7H30 à 19H","samedi":"7H30 à 19H","dimanche":"7H30 à 19H"},"phone_number":"+33596425560"},"type":"vaccination-center","vaccine_type":["Pfizer-BioNTech"]},"statsLieuSurDernieresSecondes":[{"date":"2021-05-21T10:54:32.977348+02:00","prochain_rdv":"2021-05-21T10:55:00.000000+0200","appointment_count":1019,"chronodose_appointment_count":53},{"date":"2021-05-21T10:59:31.794721+02:00","prochain_rdv":"2021-05-21T11:00:00.000000+0200","appointment_count":1018,"chronodose_appointment_count":53},{"date":"2021-05-21T11:06:03.799770+02:00","prochain_rdv":"2021-05-21T11:05:00.000000+0200","appointment_count":589,"chronodose_appointment_count":52},{"date":"2021-05-21T11:10:17.952571+02:00","prochain_rdv":"2021-05-21T11:10:00.000000+0200","appointment_count":1019,"chronodose_appointment_count":51},{"date":"2021-05-21T11:13:40.013827+02:00","prochain_rdv":"2021-05-21T11:15:00.000000+0200","appointment_count":1018,"chronodose_appointment_count":50},{"date":"2021-05-21T11:20:02.718288+02:00","prochain_rdv":"2021-05-21T11:20:00.000000+0200","appointment_count":1017,"chronodose_appointment_count":50},{"date":"2021-05-21T11:24:32.318771+02:00","prochain_rdv":"2021-05-21T11:25:00.000000+0200","appointment_count":1019,"chronodose_appointment_count":50},{"date":"2021-05-21T11:28:56.339936+02:00","prochain_rdv":"2021-05-21T11:30:00.000000+0200","appointment_count":1018,"chronodose_appointment_count":50},{"date":"2021-05-21T11:33:44.451482+02:00","prochain_rdv":null,"appointment_count":0},{"date":"2021-05-21T11:39:53.043015+02:00","prochain_rdv":"2021-05-21T11:40:00.000000+0200","appointment_count":1019,"chronodose_appointment_count":50},{"date":"2021-05-21T11:43:42.265610+02:00","prochain_rdv":"2021-05-21T11:45:00.000000+0200","appointment_count":1018,"chronodose_appointment_count":50}],"coefsDirecteur":[{"coefDirecteurStandard":0.000003346529815907395,"coefDirecteurChronodose":0,"duree":298817},{"coefDirecteurStandard":0.0010943737962525988,"coefDirecteurChronodose":0.000002550987870052678,"duree":392005},{"coefDirecteurStandard":0.00169189425267457,"coefDirecteurChronodose":0.000003934637796917605,"duree":254153},{"coefDirecteurStandard":0.000004949000549339061,"coefDirecteurChronodose":0.000004949000549339061,"duree":202061},{"coefDirecteurStandard":0.0000026129786650292,"coefDirecteurChronodose":0,"duree":382705},{"coefDirecteurStandard":0.00000741839762611276,"coefDirecteurChronodose":0,"duree":269600},{"coefDirecteurStandard":0.0000037875775033046614,"coefDirecteurChronodose":0,"duree":264021},{"coefDirecteurStandard":0.003533348142389071,"coefDirecteurChronodose":0.00017354362192480703,"duree":288112},{"coefDirecteurStandard":0.002764574380344663,"coefDirecteurChronodose":0.00013565134349090594,"duree":368592},{"coefDirecteurStandard":0.00000436258299814154,"coefDirecteurChronodose":0,"duree":229222}],"moyenneCoefsDirecteursStandardParMinute":59.05832187294018,"moyenneCoefsDirecteursChronodoseParMinute":2.095420996525263}