{"lieu":{"internal_id":"keldoc228","departement":"972","location":{"longitude":-61.0386,"latitude":14.6331,"city":"Fort-de-France","cp":"97200"},"nom":"Centre de vaccination du CHUM","url":"https://vaccination-covid.keldoc.com/centre-hospitalier-universitaire/fort-de-france-cedex-97261/centre-hospitalier-universitaire-martinique/centre-de-vaccination-du-centre-hospitalier-universitaire-martinique","appointment_by_phone_only":false,"plateforme":"Keldoc","metadata":{"address":" La Meynard, 97200 Fort-de-France","business_hours":{"lundi":"7h30 à 17h00","mardi":"7h30 à 17h00","mercredi":"7h30 à 17h00","jeudi":"7h30 à 17h00","vendredi":"7h30 à 17h00","samedi":"8h00 à 12h30","dimanche":"Fermé"},"phone_number":"+33596425560"},"type":"vaccination-center","vaccine_type":["Pfizer-BioNTech"]},"statsLieuSurDernieresSecondes":[{"date":"2021-05-21T12:09:40.367313+02:00","prochain_rdv":"2021-05-21T14:10:00.000000+0200","appointment_count":326,"chronodose_appointment_count":16},{"date":"2021-05-21T12:13:24.705133+02:00","prochain_rdv":"2021-05-21T14:20:00.000000+0200","appointment_count":325,"chronodose_appointment_count":15},{"date":"2021-05-21T12:24:19.536668+02:00","prochain_rdv":"2021-05-21T14:30:00.000000+0200","appointment_count":324,"chronodose_appointment_count":14},{"date":"2021-05-21T12:33:53.899649+02:00","prochain_rdv":"2021-05-21T14:40:00.000000+0200","appointment_count":323,"chronodose_appointment_count":13},{"date":"2021-05-21T12:49:00.387485+02:00","prochain_rdv":"2021-05-21T14:50:00.000000+0200","appointment_count":322,"chronodose_appointment_count":12},{"date":"2021-05-21T12:54:11.733421+02:00","prochain_rdv":"2021-05-21T15:00:00.000000+0200","appointment_count":321,"chronodose_appointment_count":11},{"date":"2021-05-21T13:04:28.444983+02:00","prochain_rdv":"2021-05-21T15:10:00.000000+0200","appointment_count":320,"chronodose_appointment_count":10}],"coefsDirecteur":[{"coefDirecteurStandard":0.000004457559575283724,"coefDirecteurChronodose":0.000004457559575283724,"duree":224338},{"coefDirecteurStandard":0.0000015271115753530301,"coefDirecteurChronodose":0.0000015271115753530301,"duree":654831},{"coefDirecteurStandard":0.0000017410592256116776,"coefDirecteurChronodose":0.0000017410592256116776,"duree":574363},{"coefDirecteurStandard":0.0000011031585635992974,"coefDirecteurChronodose":0.0000011031585635992974,"duree":906488},{"coefDirecteurStandard":0.000003211860759412358,"coefDirecteurChronodose":0.000003211860759412358,"duree":311346},{"coefDirecteurStandard":0.0000016215050485559687,"coefDirecteurChronodose":0.0000016215050485559687,"duree":616711}],"moyenneCoefsDirecteursStandardParMinute":0.10948648708652504,"moyenneCoefsDirecteursChronodoseParMinute":0.10948648708652504}