{"lieu":{"internal_id":"keldoc2516","departement":"974","location":{"longitude":55.3312,"latitude":-20.9358,"city":"La Possession","cp":"97419"},"nom":"Centre de vaccination COVID 19 de la Possession","url":"https://vaccination-covid.keldoc.com/redirect/?dom=centre-hospitalier&inst=la-possession-97419&user=centre-de-vaccination-la-possession&cabinet=25882&specialty=496","appointment_by_phone_only":false,"plateforme":"Keldoc","metadata":{"address":"27 b Rue Youri Gagarine, 97419 La Possession","business_hours":{"lundi":"08:30-12:45/14:30-18:00","mardi":"08:30-12:45/14:30-18:00","mercredi":"08:30-12:45/14:30-18:00","jeudi":"08:30-12:45/14:30-18:00","vendredi":"08:30-12:45/14:30-18:00","samedi":"08:30-12:45/14:30-18:00","dimanche":"fermé"},"phone_number":"+262262720404"},"type":"vaccination-center","vaccine_type":["Pfizer-BioNTech"]},"statsLieuSurDernieresSecondes":[{"date":"2021-05-22T10:44:57.936613+02:00","prochain_rdv":"2021-05-22T14:45:00.000000+0200","appointment_count":1609,"chronodose_appointment_count":81},{"date":"2021-05-22T10:48:41.353168+02:00","prochain_rdv":"2021-05-22T14:50:00.000000+0200","appointment_count":1607,"chronodose_appointment_count":79},{"date":"2021-05-22T10:54:04.293159+02:00","prochain_rdv":"2021-05-22T14:55:00.000000+0200","appointment_count":1604,"chronodose_appointment_count":78},{"date":"2021-05-22T11:04:02.775279+02:00","prochain_rdv":"2021-05-22T15:10:00.000000+0200","appointment_count":1601,"chronodose_appointment_count":74},{"date":"2021-05-22T11:10:37.544106+02:00","prochain_rdv":"2021-05-22T15:10:00.000000+0200","appointment_count":1603,"chronodose_appointment_count":74},{"date":"2021-05-22T11:13:14.764631+02:00","prochain_rdv":"2021-05-22T15:15:00.000000+0200","appointment_count":1600,"chronodose_appointment_count":72},{"date":"2021-05-22T11:19:11.833624+02:00","prochain_rdv":"2021-05-22T15:20:00.000000+0200","appointment_count":1597,"chronodose_appointment_count":69},{"date":"2021-05-22T11:24:18.542239+02:00","prochain_rdv":"2021-05-22T15:25:00.000000+0200","appointment_count":1595,"chronodose_appointment_count":67},{"date":"2021-05-22T11:29:19.283851+02:00","prochain_rdv":"2021-05-22T15:30:00.000000+0200","appointment_count":1593,"chronodose_appointment_count":65},{"date":"2021-05-22T11:33:57.004221+02:00","prochain_rdv":"2021-05-22T15:30:00.000000+0200","appointment_count":1591,"chronodose_appointment_count":63},{"date":"2021-05-22T11:40:04.929463+02:00","prochain_rdv":"2021-05-22T15:30:00.000000+0200","appointment_count":1589,"chronodose_appointment_count":61}],"coefsDirecteur":[{"coefDirecteurStandard":0.000008951870269496054,"coefDirecteurChronodose":0.000008951870269496054,"duree":223417},{"coefDirecteurStandard":0.00000928965132842014,"coefDirecteurChronodose":0.0000030965504428067135,"duree":322940},{"coefDirecteurStandard":0.000005012682085676762,"coefDirecteurChronodose":0.000006683576114235683,"duree":598482},{"coefDirecteurStandard":0.000005066253935846026,"coefDirecteurChronodose":0,"duree":394769},{"coefDirecteurStandard":0.000019081541788576516,"coefDirecteurChronodose":0.000012721027859051011,"duree":157220},{"coefDirecteurStandard":0.000008401737479310721,"coefDirecteurChronodose":0.000008401737479310721,"duree":357069},{"coefDirecteurStandard":0.0000065208389711420274,"coefDirecteurChronodose":0.0000065208389711420274,"duree":306709},{"coefDirecteurStandard":0.000006650240572452708,"coefDirecteurChronodose":0.000006650240572452708,"duree":300741},{"coefDirecteurStandard":0.00000720147198087289,"coefDirecteurChronodose":0.00000720147198087289,"duree":277721},{"coefDirecteurStandard":0.0000054358904668070935,"coefDirecteurChronodose":0.0000054358904668070935,"duree":367925}],"moyenneCoefsDirecteursStandardParMinute":0.43544089751626325,"moyenneCoefsDirecteursChronodoseParMinute":0.36286741459688604}